snakemake_executor_plugin_latch/__init__.py
snakemake_executor_plugin_latch/resource_utils.py
snakemake_executor_plugin_latch-0.1.9.dist-info/METADATA
snakemake_executor_plugin_latch-0.1.9.dist-info/WHEEL
snakemake_executor_plugin_latch-0.1.9.dist-info/RECORD
